gmmx/__init__.py
gmmx/fit.py
gmmx/gmm.py
gmmx/utils.py
gmmx-0.7.dist-info/licenses/LICENSE
gmmx-0.7.dist-info/METADATA
gmmx-0.7.dist-info/WHEEL
gmmx-0.7.dist-info/top_level.txt
gmmx-0.7.dist-info/RECORD
