Metadata-Version: 2.4
Name: gmmx
Version: 0.7
Summary: A minimal implementation of Gaussian Mixture Models in Jax
Author-email: Axel Donath <mail@axeldonath.com>
Project-URL: Homepage, https://adonath.github.io/software#gmmx
Project-URL: Repository, https://github.com/adonath/gmmx
Project-URL: Documentation, https://adonath.github.io/gmmx/
Keywords: python
Classifier: Intended Audience :: Developers
Classifier: Programming Language :: Python
Classifier: Programming Language :: Python :: 3
Classifier: Programming Language :: Python :: 3.9
Classifier: Programming Language :: Python :: 3.10
Classifier: Programming Language :: Python :: 3.11
Classifier: Programming Language :: Python :: 3.12
Classifier: Programming Language :: Python :: 3.13
Classifier: Topic :: Software Development :: Libraries :: Python Modules
Requires-Python: <4.0,>=3.9
License-File: LICENSE
Requires-Dist: jax>=0.4.30
Requires-Dist: numpy>=1.26.0
Dynamic: license-file
